{
  "id": 44952895,
  "lang": "ru",
  "summary": "- Readyset — это кеш-слой поверх MySQL/Postgres (RocksDB), который реализует «pushdown joins» с Index Condition Pushdown, давая до 450× ускорения.  \n- Суть: фильтры и условия соединения отправляются как можно ближе к данным, чтобы читать меньше строк.  \n- Участники сравнивают с JPPD в Oracle и pushdown-joins в RonDB, где такой же приём сократил время с 6 с до 50 мс.  \n- Некоторые считают это переоткрытием старых оптимизаций; другие подчёркивают, что современные оптимизаторы редко требуют «хинтов».",
  "sampleComments": [
    44997286,
    44997275,
    44996480,
    44996479,
    44996511
  ],
  "inputHash": "fd251a61490c94dd22cfaf4bf5f7d0695c398f6fa6b5cc9241962001bae4dcd7",
  "model": "moonshotai/kimi-k2:free",
  "createdISO": "2025-08-23T17:19:20.653Z"
}