{
  "id": 44964800,
  "lang": "ru",
  "summary": "- Apple и Google Photos хорошо различают животных, но не справляются с похожими серыми котами-близнецами.  \n- Участники обсуждают xAI-методы (saliency maps) для понимания, как модель отличает котов от собак, и предлагают «ExAI» как более чёткое название.  \n- Появились идеи «умной» кошачьей двери и глобальной базы данных для идентификации конкретных котов по морде, но данные и качество съёмки остаются проблемой.  \n- Кто-то уже использовал VLM для поиска пропавшей кошки среди 200 000 фото, а другие вспомнили анекдоты про «поезд, который смотрит на часы».",
  "sampleComments": [
    44999857,
    44999404,
    45000927,
    45000146,
    45000417
  ],
  "inputHash": "8b1792557e604a5cad258760cebbdc0aed26a7db8eea809c389e4c74c0907ec1",
  "model": "moonshotai/kimi-k2:free",
  "createdISO": "2025-08-24T04:30:00.918Z"
}