{
  "id": 44970563,
  "lang": "ru",
  "summary": "- Участники восторгаются креативной интеграцией «реального мира» в игры и вспоминают Miiverse в Wind Waker Wii U.  \n- Emacs сравнивают с Dwarf Fortress и EVE Online: сложно влезть, но истории завораживают.  \n- Nethack и его форки (Slashem, 3.6.7) вызывают восхищение богатством деталей и «дикими» взаимодействиями.  \n- Совет новичкам: начать с одной задачи (например, org-mode) и постепенно расширять использование.  \n- Утилита `touch` и Makefile-вариант вызывают шутки про «escape-ад».",
  "sampleComments": [
    44979531,
    44976524,
    44976946,
    44979313,
    44976775
  ],
  "inputHash": "16af93ae5ae019f5edbbd56ce9a5bc0cd8f10112e88453fa9cb8dc7f0331fb70",
  "model": "moonshotai/kimi-k2:free",
  "createdISO": "2025-08-22T01:50:32.382Z"
}