{
  "id": 44970769,
  "lang": "ru",
  "summary": "- Парquet раздроблен на две версии: v2 экономит место и ускоряет работу, но экосистема всё ещё «застряла» на v1 из-за отсутствия поддержки в Iceberg, Delta Lake и других инструментах.  \n- Справочная реализация — гигантская Java-библиотека, генерирующая десятки тысяч строк кода на каждую комбинацию параметров; участники сомневаются в её оптимальности.  \n- Даже внутри одной версии совместимость хромает: PyArrow, Fastparquet и Spark долгое время конфликтовали, как браузеры с JavaScript.  \n- Часть возможностей спецификации (например, метаданные о сортировке) фактически никем не используется.  \n- Пока крупные игроки не переведут свои стеки на v2, массового перехода не будет, и пользователям приходится выбирать между производительностью и совместимостью.",
  "sampleComments": [
    45009746,
    45007502,
    45013563,
    45007563,
    45014010
  ],
  "inputHash": "c789884b5b4c85cc96bada0aa9762ec1b356c7003fce5573ce1f374a03f098fc",
  "model": "moonshotai/kimi-k2:free",
  "createdISO": "2025-08-25T14:28:16.469Z"
}