{
  "id": 44995640,
  "lang": "ru",
  "summary": "- Спор о «плохих» символах Unicode: часть участников считает, что нужно запрещать/фильтровать проблемные код-поинты (суррогаты, управляющие символы, залго), другие — что это задача прикладного уровня, а не низкоуровневого протокола.  \n- Упоминается RFC 8264/9839 (PRECIS) как готовый список «хороших» символов для протоколов, но критики считают его слишком ограничительным.  \n- Практики делятся опытом: кто-то использует C0-символы (NUL, ESC, FF) в логах и исходниках, кто-то сталкивался с багами из-за неправильных суррогатов в UTF-16.  \n- Дискуссия о том, где именно резать строку: при парсинге JSON, при валидации поля (username) или при выводе (безопасный рендер).  \n- Общий вывод: Unicode сложен, но лучше оставить базовому формату максимальную свободу, а специфические ограничения вводить на уровне приложения.",
  "sampleComments": [
    44996118,
    44996183,
    44996052,
    44999929,
    44996801
  ],
  "inputHash": "aaf19988f5f902cdde0a7a975455656214a60cffe726e372fa34766445607a58",
  "model": "moonshotai/kimi-k2:free",
  "createdISO": "2025-08-24T05:23:55.076Z"
}