{
  "id": 45002688,
  "lang": "en",
  "tags": [
    {
      "name": "neuralink"
    },
    {
      "name": "brain-computer-interface"
    },
    {
      "name": "medical-technology"
    },
    {
      "name": "motor-cortex"
    },
    {
      "name": "deep-brain-stimulation"
    },
    {
      "name": "elon-musk"
    },
    {
      "name": "tesla"
    }
  ],
  "inputHash": "6d21803cfd4b778922774f099c2b9a463439ccbb4db88bd8b3188334ea5bacf4",
  "model": "mistralai/mistral-small-3.2-24b-instruct:free",
  "createdISO": "2025-08-26T23:21:46.610Z"
}