{
  "id": 45012615,
  "lang": "ru",
  "summary": "- Пользователь egberts1 рассказал, что купил свой первый декодер субтитров в 1976 году, когда PBS и NBC уже передавали субтитры по строкам 21/22 стандарта NTSC.  \n- Он отметил, что FCC официально стандартизировало технологию только в 1980 году, а сам декодер у него сохранился до сих пор.  \n- anthk добавил, что та же система использовалась для телетекста: котировки и новости выводились на странице 888, а субтитры можно было накладывать поверх фильма.",
  "sampleComments": [
    45021980,
    45012936
  ],
  "inputHash": "aba47407fe867312d375e3b3151b75971f89b7b01d21f8eb366ce6bc2f53fe0f",
  "model": "moonshotai/kimi-k2:free",
  "createdISO": "2025-08-26T10:26:57.922Z"
}