{
  "id": 45014656,
  "lang": "ru",
  "summary": "- TuneD существенно экономит энергию: пользователи снижали потребление с 120 Вт до 65 Вт.  \n- Есть совместимость с power-profiles-daemon через tuned-ppd, но сам PPD многим не помогал.  \n- На серверах TuneD «на 50 %» полезен; иногда проще отключить и использовать скрипты.  \n- Критика: сервис на Python, проблемы с распределением IRQ, отсутствие управления зарядом аккумулятора.  \n- Пользователи хотят утилиту для первичной диагностики Linux: suspend, GPU, Wi-Fi, диск.",
  "sampleComments": [
    45058008,
    45058442,
    45058347,
    45059655,
    45058411
  ],
  "inputHash": "28ded36811a46784bc49d2f32983f75e72cd62bd38c5928c3bf5c5d217921e38",
  "model": "moonshotai/kimi-k2:free",
  "createdISO": "2025-08-29T04:30:37.100Z"
}