{
  "id": 45021078,
  "lang": "ru",
  "summary": "- Участники спорят, почему в статье не упомянут PTP (IEEE 1588) и Linux PTP, способные обеспечить синхронизацию до <100 нс.  \n- Одни считают, что большинству пользователей хватает Chrony+NTP с качественными NIC, а PTP не работает по Wi-Fi/USB-Ethernet и требует платного стандарта.  \n- Автор отвечает, что следующая часть цикла как раз посвящена PTP, а цель текущего поста — согласованность времени, а не абсолютная точность.  \n- Обсуждаются альтернативы: White Rabbit, GPS-модули с sawtooth-коррекцией, общий 10 МГц такт.  \n- Критика методики бенчмарка: смешение x86 и ARM, игнор джиттера осциллографа, отсутствие аппаратного таймстемпинга.",
  "sampleComments": [
    45022496,
    45022158,
    45023210,
    45022397,
    45022110
  ],
  "inputHash": "b3a70d5a19264072e6b4cdfb4a7d12c9d3d885d956b4bde316554cccbaf046cc",
  "model": "moonshotai/kimi-k2:free",
  "createdISO": "2025-08-26T07:23:20.923Z"
}