{
  "id": 45056377,
  "lang": "ru",
  "summary": "- На EuroPython показали превью: главной ценностью стал прагматизм Гвидо по вопросу инклюзивности Python.  \n- Некоторые уже сравнивают фильм с документалкой про React, но мнения расходятся.  \n- Один зритель признался: любит Python, документалки и историю IT, но фильм не зацепил.  \n- Другие отметили «переосвещение» героев и клиповый стиль монтажа, который напоминает «слишком сладкие» биопики.",
  "sampleComments": [
    45100588,
    45056741,
    45095841,
    45059308,
    45097580
  ],
  "inputHash": "743ad82ae935234136838a8b2797fd21deee8f16b738647f96ffb90ccad84947",
  "model": "moonshotai/kimi-k2:free",
  "createdISO": "2025-09-02T10:27:18.877Z"
}