{
  "id": 45060004,
  "lang": "ru",
  "summary": "- libxslt — единственный C-реализация XSLT, лежащая в основе всех браузеров, но сейчас почти без поддержки; GNOME тормозит назначение нового мейнтейнера.  \n- Google отказался платить баг-баунти за найденные уязвимости, потому что исследователь сам был контрибьютором libxslt.  \n- Blink уже объявил о намерении депрекейтить и удалять XSLT, но процесс займёт годы; Firefox использует TransforMiiX, а Safari — собственный код.  \n- На практике существует много реализаций XSLT 1.0 (Saxon, Xalan, MSXML и др.), но именно libxslt используется в браузерах, поэтому её проблемы влияют на веб.  \n- Уязвимости актуальны, если выполнять чужие XSLT-стили; для собственных преобразований непроверенного XML риск ниже.",
  "sampleComments": [
    45061821,
    45060826,
    45061479,
    45061377,
    45063560
  ],
  "inputHash": "ed79bb91366d3b16ad0b567953b97d3af885118103d532a8201519540d76f449",
  "model": "moonshotai/kimi-k2:free",
  "createdISO": "2025-08-29T14:27:07.923Z"
}