{
  "id": 45066999,
  "lang": "en",
  "tags": [
    {
      "name": "sqlite"
    },
    {
      "name": "durability"
    },
    {
      "name": "database"
    },
    {
      "name": "journal-mode"
    },
    {
      "name": "fsync"
    },
    {
      "name": "wal"
    },
    {
      "name": "synchronous"
    },
    {
      "name": "pragmas"
    }
  ],
  "inputHash": "77058174aab8fb0a99098cf0891b4534da951a841fa4e81df1d1c5e96830ef0a",
  "model": "mistralai/mistral-small-3.2-24b-instruct:free",
  "createdISO": "2025-08-30T01:46:02.243Z"
}