{
  "id": 45084126,
  "lang": "ru",
  "summary": "- Участники сомневаются, что ActivityPub позволит каждому хранить полную копию своих данных локально.  \n- Проблема в восстановлении: нет удобных серверов, которые «подтягивают» старые посты, а URL-идентификаторы ломаются при переносе.  \n- В AT-экосистеме уже тестируются приложения для локального хранения, но их названия никто не вспомнил.  \n- Есть лишь внешний инструмент бэкапа (storacha.network), но он не решает вопрос переноса и целостности ссылок.",
  "sampleComments": [
    45086396,
    45087448,
    45087018
  ],
  "inputHash": "d7d4fc472cc6f1362475a7ea2939044236a3679618657ccc8ac0da568eeac13e",
  "model": "moonshotai/kimi-k2:free",
  "createdISO": "2025-08-31T22:24:25.144Z"
}