{
  "id": 45092204,
  "lang": "ru",
  "summary": "- Обсуждение показало, что «кастомные ROM» для машин в духе Android-устройств не существуют: автомобиль — это система систем, связанных через CAN-BUS, и безопасность/ответственность не позволяют просто прошивать новую прошивку.  \n- Есть лишь точечные примеры: открытые ECU, тюнеры, прошивки мультимедиа (M.I.B., MazdaTweaks, OrBit для Volvo/Polestar) и аппаратные решения вроде Comma.ai Openpilot, которые лишь «говорят» по CAN-BUS или модифицируют отдельные блоки.  \n- Прошивки подписываются и проверяются на подлинность, а железо сильно привязано к конкретной платформе, что делает портирование ROM практически невозможным.  \n- Правовая ответственность и страх перед последствиями аварий тормозят любые попытки создать полноценный open-source «автомобильный ROM».",
  "sampleComments": [
    45093327,
    45093097,
    45093035,
    45093037,
    45093000
  ],
  "inputHash": "b5b98de69abc9f418888a38c547acbaa08c2a2ae45ff23f1473aaf0acfcd539d",
  "model": "moonshotai/kimi-k2:free",
  "createdISO": "2025-09-01T15:26:23.267Z"
}