{
  "id": 45092925,
  "lang": "ru",
  "summary": "- Google AI Overview приписало музыканту Benn Jordan видео «Was Wrong About Israel» другого автора (Ryan McBeth), выдав вымышленную дату 18 августа 2025.  \n- Участники обсуждения считают это ярким примером опасности «галлюцинаций» ИИ: ложь становится заголовками, а пользователи без проверки верят результатам.  \n- Многие подчеркивают, что мелкий дисклеймер «AI может ошибаться» не решает проблему репутационного ущерба и требуют юридической ответственности Google.  \n- Приводятся аналогичные случаи: мелкому бизнесу приписывают мошенничество, людям — смерть, а HR-системы уже фильтруют кандидатов по ошибочным AI-досье.  \n- Общий вывод: общественно значимые системы запущены на публику как бета-тест без должной безопасности, и без законодательного давления ситуация ухудшится.",
  "sampleComments": [
    45093447,
    45093284,
    45094942,
    45093734,
    45093187
  ],
  "inputHash": "6d5cf1e15c82fc71c94741602fe7c4fd03d055d5c4009b9dcbf0b6f634b8380a",
  "model": "moonshotai/kimi-k2:free",
  "createdISO": "2025-09-01T23:23:30.956Z"
}