{
  "id": 45105339,
  "lang": "ru",
  "summary": "**Сколько энергии тратит Visual Look Up?**\n\nVLU на M4 Pro активно грузит CPU и нейро-движок (ANE).  \nИзмерения `powermetrics` (шаг 100 мс) показали:\n\n- **6,5 с** активной работы;\n- **6,9 Дж** суммарно;\n- **93 %** энергии — CPU, **4,6 %** — GPU, **2,2 %** — ANE;\n- пик CPU: **7 Вт**, ANE: **0,7 Вт**.\n\nЛог зафиксировал четыре подряд вызова ANE (1,4–2,2 с) и финальный запрос к серверу Apple.",
  "inputHash": "133af1eb199ad02366b0327749dceb41517602c04192aa1684214517ab1799e8",
  "model": "moonshotai/kimi-k2:free",
  "createdISO": "2025-09-06T12:43:45.646Z"
}