{
  "id": 45110688,
  "lang": "en",
  "tags": [
    {
      "name": "cpu"
    },
    {
      "name": "hyperthreading"
    },
    {
      "name": "turbo-boost"
    },
    {
      "name": "performance-benchmarking"
    },
    {
      "name": "stress-ng"
    },
    {
      "name": "multithreading"
    },
    {
      "name": "system-monitoring"
    },
    {
      "name": "amd"
    },
    {
      "name": "intel"
    },
    {
      "name": "gpu"
    }
  ],
  "inputHash": "8cbc4d11736981e116193243e214c10a4b876c8be8c12add2885f57e56df29d4",
  "model": "mistralai/mistral-small-3.2-24b-instruct:free",
  "createdISO": "2025-09-03T02:57:25.591Z"
}