{
  "id": 45152779,
  "lang": "en",
  "tags": [
    {
      "name": "555-timer"
    },
    {
      "name": "navajo-weaving"
    },
    {
      "name": "integrated-circuits"
    },
    {
      "name": "electronics"
    },
    {
      "name": "art"
    },
    {
      "name": "microelectronics"
    },
    {
      "name": "jacob-loom"
    },
    {
      "name": "circuit-design"
    }
  ],
  "inputHash": "99245c37bc13e0d90b67da8a73fd0c2865ba2ebf1bb75bef7ab432bd5bff83f5",
  "model": "mistralai/mistral-small-3.2-24b-instruct:free",
  "createdISO": "2025-09-07T05:20:15.271Z"
}