{
  "id": 45236574,
  "lang": "ru",
  "summary": "- Пользователь @yogorenapan признаёт, что Kubernetes ему не критичен, но привлекает мощным инструментарием; переход занял месяц обучения и отладки, после чего стал простым.  \n- @bratao хвалит Rancher для кластера на десятках выделенных серверов и ищет совет по удобным CI/CD-решениям для команды из 30 человек.",
  "sampleComments": [
    45237030,
    45237034
  ],
  "inputHash": "b59b44f68a6bc8c9d508cf24ad8c4cb28e37ff02044e0afe1c8be662571a4c37",
  "model": "moonshotai/kimi-k2:free",
  "createdISO": "2025-09-14T03:06:03.928Z"
}