{
  "id": 45354404,
  "lang": "en",
  "tags": [
    {
      "name": "commodore-64"
    },
    {
      "name": "meshtastic"
    },
    {
      "name": "lora"
    },
    {
      "name": "basic"
    },
    {
      "name": "mesh-networking"
    },
    {
      "name": "peer-to-peer"
    },
    {
      "name": "protobuf"
    }
  ],
  "inputHash": "b0acd4fd657df54fa7531bbb670f435c65f2b1a07c0af4218f9af00b1fedb140",
  "model": "mistralai/mistral-small-3.2-24b-instruct:free",
  "createdISO": "2025-09-27T15:28:00.956Z"
}