{
  "id": 45574393,
  "lang": "en",
  "tags": [
    {
      "name": "ddos"
    },
    {
      "name": "botnet"
    },
    {
      "name": "iot"
    },
    {
      "name": "dns"
    },
    {
      "name": "cloudflare"
    },
    {
      "name": "akamai"
    },
    {
      "name": "nullroute"
    },
    {
      "name": "counter-strike-2"
    },
    {
      "name": "minecraft"
    }
  ],
  "inputHash": "d3a9da49303125b460fa661531d2c013650abcbad898150b01f0ba11e131170e",
  "model": "mistralai/mistral-small-3.2-24b-instruct:free",
  "createdISO": "2025-10-14T01:47:10.406Z"
}