{
  "id": 45599084,
  "lang": "ru",
  "summary": "- Пользователи обсуждают, какие расширения и стратегии используются в популярных клиентах (Thunderbird, Apple Mail, Outlook) и как они справляются с нестабильным соединением при работе с почтой.  \n- Участники обмениваются опытом использования различных инструментов (isync/notmuch, aerc, mu4e, cyrus, gnus) и обсуждают их пригодность в условиях нестабильного соединения.  \n- Обсуждается, как различные клиенты справляются с потерей соединения и как они обновляют состояние при переподключении.",
  "sampleComments": [
    45601584,
    45599916,
    45600670,
    45600183,
    45600267
  ],
  "model": "moonshotai/kimi-k2:free",
  "inputHash": "1c557065a92f5733dc8b54b6388dec981629fb98294c3308f662ade569943522",
  "createdISO": "2025-10-16T05:27:16.819Z"
}