{
  "id": 45615931,
  "lang": "ru",
  "summary": "- Люди делятся ссылками на живые потоки из Намиба, где слоны, жирафы и другие животные приходят к водопою в пустыне Намиб.  \n- Пользователи обсуждают, как технически устроен такой поток, какие камеры и микрофоны используются, и как можно повторить это дома.  \n- Сообщество обсуждает, как технологические гиганты вроде Google и Netflix могли бы интегрировать такие потоки в свои продукты, чтобы уменьшить «черные экраны» в квартирах и офисах.  \n- Участники делятся личными историями о том, как наблюдение за этими потоками влияет на их продуктивность и мотивацию.  \n- Обсуждается, как такие потоки могут быть использованы в образовании, в особенности для детей, которые растут в городских условиях.",
  "sampleComments": [
    45616575,
    45618190,
    45616218,
    45616257,
    45619906
  ],
  "model": "moonshotai/kimi-k2:free",
  "inputHash": "53c64a60ae7a57950485b9e8e588601d528e3e0eb557ec409b81628e43517260",
  "createdISO": "2025-10-17T19:23:45.228Z"
}