{
  "id": 45675015,
  "lang": "ru",
  "summary": "- Google Safe Browsing флагнул домен, используемый для self-hosting, что вызвало обсуждение о том, как Google определяет \"опасные\" сайты и почему это может быть проблемой для самостоятельно хостящих сервисов.\n- Участники обсуждения подчеркнули, что Google не предоставляет ясной информации о том, что именно вызвало флаг, и что это может быть вызвано ложным срабатыванием.\n- Обсуждение также затронуло вопрос о том, как Google может влиять на веб-разработчиков и их клиентов, и как это может быть связано с их бизнесом.\n- Участники также обсуждали, что Google может использовать свою позицию в рынке браузеров и поисковых систем для продвижения своих собственных продуктов и услуг.\n- Некоторые участники выразили обеспокоенность о том, что Google может использовать эту систему для сбора данных о пользователях и их действиях в интернете.\n- В конце обсуждения участники обсудили, что может быть сделано для защиты от таких проблем в будущем, включая разделение доменов для разных целей и использование Public Suffix List.",
  "sampleComments": [
    45678446,
    45679583,
    45676475,
    45676467,
    45677260
  ],
  "model": "moonshotai/kimi-k2:free",
  "inputHash": "5f77c45a198aaf7c72afb8d81e4cde200bbfb5e41d5a74c6f3b0128ba40c6201",
  "createdISO": "2025-10-23T10:29:33.617Z"
}