{
  "id": 45711577,
  "lang": "ru",
  "summary": "-   Путаница из-за двойственности заголовка: многие ожидали философского или культурного смысла (\"как римляне воспринимали себя/мир\"), а статья оказалась о буквальных зеркалах.\n-   Культурные искажения: современные представления об античности (например, мраморные статуи без краски) сильно отличаются от первоначального вида из-за времени и утраты деталей (патина, утрата цвета).\n-   Важность экспериментальной археологии: для понимания истинного вида древних предметов (зеркал, статуй) необходимы современные реплики и исследования исходных материалов (полированные металлы, стекло с покрытием).\n-   Технологическое влияние: зеркала как технология могли оказывать глубокое, но забытое влияние на культуру и восприятие людей.",
  "sampleComments": [
    45757089,
    45756658,
    45756482,
    45756329,
    45756597
  ],
  "model": "z-ai/glm-4.5-air:free",
  "inputHash": "439bb7d162e6c2f1ee6ab6bf866185d9a6d41c547a7a4023573697cffe8788b6",
  "createdISO": "2025-10-30T07:29:08.557Z"
}