{
  "id": 45832051,
  "lang": "en",
  "tags": [
    {
      "name": "javascript"
    },
    {
      "name": "rust"
    },
    {
      "name": "ecmascript"
    },
    {
      "name": "servo"
    },
    {
      "name": "v8"
    },
    {
      "name": "spidermonkey"
    },
    {
      "name": "lua"
    },
    {
      "name": "github"
    }
  ],
  "inputHash": "2d1e9a26b89784a1ee060f969f387b744dca2845b9cb2a528e8a970ee73a01ab",
  "model": "mistralai/mistral-small-3.2-24b-instruct:free",
  "createdISO": "2025-11-16T07:36:27.749Z"
}