{
  "id": 45842419,
  "lang": "ru",
  "summary": "- Пользователь автоматизирует ежедневные напоминания через скрипт, проверяющий события в remind, и уведомляющий звуком, email и SMS.\n- Поднимается вопрос о сложности текстовых инструментов: их избыточность и непользовательский подход критикуются как \"программирование шаттла для покупки мороженого\".\n- Защищается универсальность текстовых инструментов: они легко интегрируются в рабочие процессы и обеспечивают гибкость после первоначальной настройки.\n- Пользователи активно используют remind в bash-скриптах для персонализации интерфейса и генерации календарей.\n- Интересуются практической реализацией \"системы оповещений дома\" как части автоматизации.",
  "sampleComments": [
    45920829,
    45923503,
    45923080,
    45920582,
    45922544
  ],
  "model": "z-ai/glm-4.5-air:free",
  "inputHash": "1c836a82b03aecf95415f1f2896928b94e6c8776df0cb1b3ef58d6ac2953d295",
  "createdISO": "2025-11-14T05:43:16.474Z"
}