{
  "id": 45852854,
  "lang": "en",
  "tags": [
    {
      "name": "cross-platform"
    },
    {
      "name": "ui"
    },
    {
      "name": "mobile"
    },
    {
      "name": "desktop"
    },
    {
      "name": "native"
    },
    {
      "name": "performance"
    },
    {
      "name": "react-native"
    },
    {
      "name": "flutter"
    },
    {
      "name": "pwa"
    },
    {
      "name": "snapchat"
    }
  ],
  "inputHash": "cd887e69432f7d5257d28099b39948ebfb0d88de37cf4170ad0d18a3b7360972",
  "model": "mistralai/mistral-small-3.2-24b-instruct:free",
  "createdISO": "2025-11-09T07:29:51.974Z"
}