{
  "id": 46057488,
  "lang": "ru",
  "summary": "- Voyager 1 приближается к расстоянию в 1 световой день от Земли, задержка связи составит ~сутки на команду и ответ.\n- Восхищение надежностью технологий 1970-х: зонд работает полвека в космосе, в отличие от хрупких современных микросервисов.\n- Размышления о масштабах космоса: 75 тыс. лет до ближайшей звезды, призывы защищать Землю как единственный дом.\n- Идеи о будущих миссиях: цепочки реле, догонялки зондов, частные межзвездные проекты от миллиардеров.\n- Критика статьи: misleading заголовок (\"about to\" — через год), неточности в задержках (Марс до 22 мин), ссылки на HN.",
  "sampleComments": [
    46069798,
    46057922,
    46058528,
    46067107,
    46058532
  ],
  "model": "x-ai/grok-4.1-fast:free",
  "inputHash": "aec0a5e9f8743e26f2e6d8fe3ab8b4dfe5974f60f70a89f61e4479cc5be93ec6",
  "createdISO": "2025-11-27T16:46:24.095Z"
}