[
  {
    "id": 44932952,
    "by": "AbuAssar",
    "timeISO": "2025-08-17T16:48:35.000Z",
    "textPlain": "This is confusing to say the least, the US are providing Israel with heavy hardware and ammunition to kill the Palestinian civilians, and then they want to take the children victims for medical care?!Why the US plays on both sides?",
    "parent": 44932487,
    "depth": 1
  },
  {
    "id": 44932606,
    "by": "laurent_du",
    "timeISO": "2025-08-17T16:08:57.000Z",
    "textPlain": "I didn't expect the article to conclude with a pg quote from twitter. Why did they  think pg was a notable authority on the matter of human rights? I am not asking in snark, just curious.",
    "parent": 44932487,
    "depth": 1
  },
  {
    "id": 44933071,
    "by": "cwmoore",
    "timeISO": "2025-08-17T17:03:50.000Z",
    "textPlain": "Does Egypt have a border with Gaza?",
    "parent": 44932487,
    "depth": 1
  },
  {
    "id": 44932890,
    "by": "skybrian",
    "timeISO": "2025-08-17T16:41:32.000Z",
    "textPlain": "> An Ohio-based humanitarian group, HEAL Palestine, is the main American organization helping evacuate people — primarily injured children and family members — and bringing them to several cities in the U.S. for medical treatment. According to the organization's website, it has evacuated 148 people from Gaza, including 63 children.https://www.npr.org/2025/08/16/nx-s1-5504634/state-departmen...Are there similar organizations operating in other countries?",
    "parent": 44932487,
    "depth": 1
  },
  {
    "id": 44932731,
    "by": "artninja1988",
    "timeISO": "2025-08-17T16:24:00.000Z",
    "textPlain": "They have a point in that Israel should be forced to take care of those children, also to stop the genocide. Taking in displaced only serves Israels interests",
    "parent": 44932487,
    "depth": 1
  },
  {
    "id": 44932931,
    "by": "Slava_Propanei",
    "timeISO": "2025-08-17T16:45:29.000Z",
    "textPlain": "[dead]",
    "parent": 44932487,
    "depth": 1
  },
  {
    "id": 44932696,
    "by": "like_any_other",
    "timeISO": "2025-08-17T16:20:10.000Z",
    "textPlain": "[flagged]",
    "parent": 44932487,
    "depth": 1
  },
  {
    "id": 44932488,
    "by": "NomDePlum",
    "timeISO": "2025-08-17T15:54:42.000Z",
    "textPlain": "Full title: US state department stops issuing visas for Gaza’s children to get medical care after far-right campaign",
    "parent": 44932487,
    "depth": 1
  },
  {
    "id": 44933012,
    "by": "dathinab",
    "timeISO": "2025-08-17T16:56:41.000Z",
    "textPlain": "because- it's about civilians and at least the official stance is that the US helps Israel to fight terrorist, not civilians.- a government isn't a single person- this doesn't just involves the US government but also humanitarian help groups",
    "parent": 44932952,
    "depth": 2
  },
  {
    "id": 44933133,
    "by": "mc32",
    "timeISO": "2025-08-17T17:11:51.000Z",
    "textPlain": "Question is, are there not medical facilities within a 500 mile radius who would be willing to take these patients in, if not, why aren’t they taking them in?Like why fly people 5,000 knots instead of 500? The EMEA region has hospitals and physicians just as good as those in other continents.",
    "parent": 44932952,
    "depth": 2
  },
  {
    "id": 44933016,
    "by": "wat10000",
    "timeISO": "2025-08-17T16:57:22.000Z",
    "textPlain": "“The US” is not providing medical care for the victims. A private charity is. The role of the US government is in allowing, or now denying, the recipients to enter the country to receive care.",
    "parent": 44932952,
    "depth": 2
  },
  {
    "id": 44932989,
    "by": "s5300",
    "timeISO": "2025-08-17T16:53:49.000Z",
    "textPlain": ">> This is confusing to say the least, the US are providing Israel with heavy hardware and ammunition to kill the Palestinian civilians, and then they want to take the children victims for medical care?!\nWhy the US plays on both sides?The US taxpayer has always paid for Israel’s citizens healthcare, while US citizens go without healthcare and ration their necessary medicine. Makes you wonder how such leverage can exist.",
    "parent": 44932952,
    "depth": 2
  },
  {
    "id": 44933072,
    "by": "seadan83",
    "timeISO": "2025-08-17T17:04:02.000Z",
    "textPlain": "It's an example of notable criticism. The campaign was on twitter, so the PG quote is context and as an example of what detractors are saying.",
    "parent": 44932606,
    "depth": 2
  },
  {
    "id": 44932932,
    "by": "nojs",
    "timeISO": "2025-08-17T16:46:00.000Z",
    "textPlain": "Writing a summary of twitter hot takes is easier than doing actual research.",
    "parent": 44932606,
    "depth": 2
  },
  {
    "id": 44932842,
    "by": "BallsInIt",
    "timeISO": "2025-08-17T16:37:00.000Z",
    "textPlain": "To prevent the story from getting flagged on HN.",
    "parent": 44932606,
    "depth": 2
  },
  {
    "id": 44933150,
    "by": "Cyph0n",
    "timeISO": "2025-08-17T17:13:05.000Z",
    "textPlain": "Yes. That is how these patients were being evacuated in the first place before traveling to the US for treatment.",
    "parent": 44933071,
    "depth": 2
  },
  {
    "id": 44933049,
    "by": "williamscales",
    "timeISO": "2025-08-17T17:01:22.000Z",
    "textPlain": "The WHO is organizing some evacuations internationally> the World Health Organization supported the transfer of 32 children and six adults to Italy, Belgium and Turkey, but more than 14,800 patients are still waiting.https://www.theguardian.com/world/2025/aug/16/malnourished-p...",
    "parent": 44932890,
    "depth": 2
  },
  {
    "id": 44932877,
    "by": "nemomarx",
    "timeISO": "2025-08-17T16:40:35.000Z",
    "textPlain": "Since Israel is not going to do either, and the US is not going to try and make them, I think we should at least save the lives we can. Imagine asking Germany in the 40s to take better care of Jewish children to turn away refugees, right?",
    "parent": 44932731,
    "depth": 2
  },
  {
    "id": 44932990,
    "by": "worldsavior",
    "timeISO": "2025-08-17T16:53:59.000Z",
    "textPlain": "There is no law requiring two enemies to take care of each other citizens. Israel provides Gaza with a few big human rights organizations, primarily the UN, to operate in Gaza and serve those \"in need\". They don't block food or other humanitarian aids. Actually, Israel has put tons of food aid outside of Gaza waiting to be taken by trucks of the UN, and they never came.Hamas never took care of the women and children of Israel on October 7th, obviously they did the opposite. Maybe you should tell Hamas to take care of it's people at least?",
    "parent": 44932731,
    "depth": 2
  },
  {
    "id": 44932936,
    "by": "Slava_Propanei",
    "timeISO": "2025-08-17T16:46:15.000Z",
    "textPlain": "[dead]",
    "parent": 44932731,
    "depth": 2
  },
  {
    "id": 44932917,
    "by": "DSingularity",
    "timeISO": "2025-08-17T16:43:57.000Z",
    "textPlain": "Hard agree. I am highly sympathetic to the numerous tragedies that have afflicted the modern Palestinians. They have only knowing suffering at the hands of overwhelming adversaries from the British colonial rule to the rule of western armed Eastern European terrorist gangs.That being said if we take in Palestinians we are effectively advancing the self proclaimed objective of the Israeli government: ethnic cleansing. The west should not take them in and the west should instead sanction Israel to the point of crippling their economy. Only then will the Israelis stop the abuse.",
    "parent": 44932731,
    "depth": 2
  },
  {
    "id": 44932925,
    "by": "virgildotcodes",
    "timeISO": "2025-08-17T16:44:50.000Z",
    "textPlain": "Of course, someone can be jewish and be far right. Someone can be black and own black slaves. Someone can be a woman and be against women's suffrage. Someone can be rich or poor and a class traitor, etc etc.Someone's identity can and often does influence their politics, but they are not always in alignment, and their identity certainly doesn't negate their positions that are harmful towards others the share parts of their identity (all of this is often done in exchange for personal gain with these famous people who make a living off all this).",
    "parent": 44932696,
    "depth": 2
  },
  {
    "id": 44932976,
    "by": "Levitz",
    "timeISO": "2025-08-17T16:52:27.000Z",
    "textPlain": "I don't see how Jewish ancestry has any actual relevance, especially given the \"proud islamophobe\" quote.No matter how much overlap there is between Jews and Zionists, it is one thing to criticize someone for their position on something and a whole different thing to criticize them for their ethnicity. That \"whole different thing\" is prejudice, which helps nobody here.",
    "parent": 44932696,
    "depth": 2
  },
  {
    "id": 44932849,
    "by": "PeakKS",
    "timeISO": "2025-08-17T16:37:33.000Z",
    "textPlain": "Those two attributes are not contradictory.",
    "parent": 44932696,
    "depth": 2
  },
  {
    "id": 44932893,
    "by": "AlecSchueler",
    "timeISO": "2025-08-17T16:41:38.000Z",
    "textPlain": "Surely Jews can have differing beliefs?",
    "parent": 44932696,
    "depth": 2
  },
  {
    "id": 44932911,
    "by": "seadan83",
    "timeISO": "2025-08-17T16:43:40.000Z",
    "textPlain": "Every fact about Laura loomer could be wrong, doesn't change the cruelty of the policy change.The VERY FIRST SENTENCE of your wikipedia link says: \"Laura Elizabeth Loomer (born May 21, 1993) is an American FAR-RIGHT political activist, conspiracy theorist,[b] and internet personality.\" (caps added for emphasis)",
    "parent": 44932696,
    "depth": 2
  }
]