[
  {
    "id": 44982249,
    "by": "boredpudding",
    "timeISO": "2025-08-22T08:45:42.000Z",
    "textPlain": "It's solved, full write-up here: https://www.reddit.com/r/MinecraftUnlimited/comments/1cvo5py...Tl:dr; It was a release file for their Minecon event. It was never meant to be public. Obsessing over a password protected in a company's S3 bucket is weird and crosses many limits.",
    "parent": 44981802,
    "depth": 1
  },
  {
    "id": 44982385,
    "by": "djmips",
    "timeISO": "2025-08-22T09:07:54.000Z",
    "textPlain": "Telling people they should not try and crack something is kind of like the Streisand effect.",
    "parent": 44982249,
    "depth": 2
  },
  {
    "id": 44982401,
    "by": "charcircuit",
    "timeISO": "2025-08-22T09:10:05.000Z",
    "textPlain": ">is weird and crosses many limits.It's similar in format to communities that obssess over \"lost media.\" The inability to pirate or get access to something becomes an obsession. Even if the piece of media exists in an archive somewhere, that doesn't matter to them because it's about the fact that they themselves don't have access to it that has become the obsession.",
    "parent": 44982249,
    "depth": 2
  }
]