[
  {
    "id": 45026221,
    "by": "neonate",
    "timeISO": "2025-08-26T13:24:54.000Z",
    "textPlain": "https://web.archive.org/web/20250816000000/https://linusakes...",
    "parent": 45024847,
    "depth": 1
  },
  {
    "id": 45029163,
    "by": "vivzkestrel",
    "timeISO": "2025-08-26T16:53:00.000Z",
    "textPlain": "kindly put the comment section inside an expandable accordion or something, it takes 90% of the scrollbar space on your page currently. i initially thought it is a 500,000 word article only to scroll down 5 pages and see rest of everything is comments",
    "parent": 45024847,
    "depth": 1
  },
  {
    "id": 45028716,
    "by": "wowczarek",
    "timeISO": "2025-08-26T16:24:25.000Z",
    "textPlain": "The term Line Discipline gets me every time, it's right up there with Kernel, Shell and Terminal and always takes me back to my first contact with Unix and Unix-like systems. Felt like being eight years old and being allowed to pet a real dinosaur.",
    "parent": 45024847,
    "depth": 1
  },
  {
    "id": 45026185,
    "by": "tomhow",
    "timeISO": "2025-08-26T13:22:35.000Z",
    "textPlain": "The TTY Demystified (2008) - https://news.ycombinator.com/item?id=31146862 - April 2022 (22 comments)The TTY Demystified (2008) - https://news.ycombinator.com/item?id=26803109 - April 2021 (35 comments)The TTY demystified (2008) - https://news.ycombinator.com/item?id=17765683 - Aug 2018 (12 comments)The TTY demystified (2008) - https://news.ycombinator.com/item?id=13571055 - Feb 2017 (43 comments)The TTY demystified (2008) - https://news.ycombinator.com/item?id=10631513 - Nov 2015 (40 comments)The TTY demystified (2008) - https://news.ycombinator.com/item?id=10064657 - Aug 2015 (31 comments)The TTY Demystified (2008) - https://news.ycombinator.com/item?id=4544318 - Sept 2012 (46 comments)The TTY demystified (2008) - https://news.ycombinator.com/item?id=4062981 - June 2012 (17 comments)The TTY demystified - https://news.ycombinator.com/item?id=658155 - June 2009 (13 comments)",
    "parent": 45024847,
    "depth": 1
  },
  {
    "id": 45026186,
    "by": "dark-star",
    "timeISO": "2025-08-26T13:22:37.000Z",
    "textPlain": "The site only says  pg_connect:\n\nfor me. Broken? HN hug of death?",
    "parent": 45024847,
    "depth": 1
  },
  {
    "id": 45027468,
    "by": "unit149",
    "timeISO": "2025-08-26T14:56:03.000Z",
    "textPlain": "[dead]",
    "parent": 45024847,
    "depth": 1
  },
  {
    "id": 45026257,
    "by": "jonasdegendt",
    "timeISO": "2025-08-26T13:27:37.000Z",
    "textPlain": "Alas, hugged indeed it seems like, someone posted an archive link!",
    "parent": 45026186,
    "depth": 2
  }
]