[
  {
    "id": 45123899,
    "by": "floren",
    "timeISO": "2025-09-04T05:32:01.000Z",
    "textPlain": "I'm still figuring out how to integrate this with my existing wearable system. I've been using a Vufine monocular display which is nice as a real HDMI screen but the wire is clunky. So far I'm experimenting with extending the Python code to read images from a directory and display them, newest first... from that I see a path to doing useful stuff with notifications, even turn by turn navigation.",
    "parent": 45087803,
    "depth": 1
  },
  {
    "id": 45123909,
    "by": "cik",
    "timeISO": "2025-09-04T05:34:30.000Z",
    "textPlain": "This is the first time I've seen the product, and I was immediately excited.. until I saw the product.Now, I don't know what it does that my $40 smart watch doesn't do, by passing my voice to google / alexa / <choice>.  I like where this is going, I just don't think that this generation has even the same features, as what I carry on my wrist, sadly.",
    "parent": 45087803,
    "depth": 1
  },
  {
    "id": 45123349,
    "by": "gibolt",
    "timeISO": "2025-09-04T03:48:35.000Z",
    "textPlain": "The project looks super cool, but the idea of wearing a sharp screen that close to my eye on a bike could be one reason it didn't sell.",
    "parent": 45087803,
    "depth": 1
  },
  {
    "id": 45123975,
    "by": "Jolter",
    "timeISO": "2025-09-04T05:51:20.000Z",
    "textPlain": "It’s a cancelled product from 2018, you shouldn’t expect to be wowed if you’re comparing it to the current state of the wearable art.",
    "parent": 45123909,
    "depth": 2
  },
  {
    "id": 45123954,
    "by": "blensor",
    "timeISO": "2025-09-04T05:46:12.000Z",
    "textPlain": "I found this yesterday https://minimis.life/ it also has cycling in mind based off their description",
    "parent": 45123349,
    "depth": 2
  },
  {
    "id": 45123879,
    "by": "floren",
    "timeISO": "2025-09-04T05:27:29.000Z",
    "textPlain": "I wouldn't really have any reservations with the glasses insert in, I think it would protect well enough.",
    "parent": 45123349,
    "depth": 2
  }
]