[
  {
    "id": 45165047,
    "by": "xg15",
    "timeISO": "2025-09-08T06:02:10.000Z",
    "textPlain": "> Yet, this common-sense definition is unsatisfying if we consider that a lower-dimensional object might end up straddling a higher-dimensional space. If a line segment is rotated or bent, does that make it 2D? Or is that object forever one-dimensional, somehow retaining the memory of its original orientation and curvature?Isn't that exactly what topological manifolds are for?https://en.wikipedia.org/wiki/Manifold",
    "parent": 45124560,
    "depth": 1
  },
  {
    "id": 45164537,
    "by": "tzury",
    "timeISO": "2025-09-08T04:04:51.000Z",
    "textPlain": "one of the most precious resources on the internet about dimensions is herehttps://www.youtube.com/playlist?list=PL3C690048E1531DC7walks you through step by step, builds the intuition and provides some historical context in the background.despite \"outdated\" animation (15 years ago), still a great resource.also available in 7 other languages.",
    "parent": 45124560,
    "depth": 1
  },
  {
    "id": 45164193,
    "by": "swayvil",
    "timeISO": "2025-09-08T02:33:43.000Z",
    "textPlain": "Why do people disable zoom on their page?",
    "parent": 45124560,
    "depth": 1
  }
]