[
  {
    "id": 45246855,
    "by": "SkiFire13",
    "timeISO": "2025-09-15T06:53:19.000Z",
    "textPlain": "I feel like this article would be much more approachable if it didn't assume readers already know Ocaml and Haskell and their module system",
    "parent": 45221112,
    "depth": 1
  },
  {
    "id": 45247924,
    "by": "indigoabstract",
    "timeISO": "2025-09-15T09:52:43.000Z",
    "textPlain": "Delightfully weird and niche article.And I wouldn't be surprised if there were more retired left handed surgeons in their 50s living in rural Switzerland than people who understand what he's talking about.",
    "parent": 45221112,
    "depth": 1
  },
  {
    "id": 45247138,
    "by": "test6554",
    "timeISO": "2025-09-15T07:42:17.000Z",
    "textPlain": "I just picture Charlie from “It’s Always Sunny in Philadelphia” connecting the dots.",
    "parent": 45221112,
    "depth": 1
  },
  {
    "id": 45247820,
    "by": "semiinfinitely",
    "timeISO": "2025-09-15T09:35:43.000Z",
    "textPlain": "even for someone moderately interested in FP, this one goes above my head and the only take-away I can get from it is \"maybe use ocaml instead of haskell\"",
    "parent": 45221112,
    "depth": 1
  },
  {
    "id": 45247714,
    "by": "b_e_n_t_o_n",
    "timeISO": "2025-09-15T09:20:28.000Z",
    "textPlain": "if err !== nil {\n      return err\n   }",
    "parent": 45221112,
    "depth": 1
  },
  {
    "id": 45247653,
    "by": "12_throw_away",
    "timeISO": "2025-09-15T09:08:59.000Z",
    "textPlain": "\"Functors\" \"Monads\" \"Typeclasses\" <- concepts dreamed up by the utterly deranged",
    "parent": 45221112,
    "depth": 1
  },
  {
    "id": 45247192,
    "by": "nine_k",
    "timeISO": "2025-09-15T07:51:58.000Z",
    "textPlain": "Indeed so, but that would require a few months worth of work from the reader, unfortunately.(I have a t-shirt with a lambda in a circle, reminiscent of the anarchist emblem, and words \"no class, no state\". It's definitely possible to explain to a passer-by who never studied FP what it refers to, but not in such a way that the joke remained funny. Possibly the same deal is with the bumper sticker saying \"my other car is cdr\".)",
    "parent": 45246855,
    "depth": 2
  },
  {
    "id": 45247397,
    "by": "fweimer",
    "timeISO": "2025-09-15T08:28:13.000Z",
    "textPlain": "Haskell knowledge doesn't actually help because this isn't using the (very barebones) Haskell module system, but the Backpack extension: https://www.microsoft.com/en-us/research/wp-content/uploads/...",
    "parent": 45246855,
    "depth": 2
  },
  {
    "id": 45247893,
    "by": "nesarkvechnep",
    "timeISO": "2025-09-15T09:47:55.000Z",
    "textPlain": "Yeah, it’s better to not assume anything and be stuck in the basics forever, right?",
    "parent": 45246855,
    "depth": 2
  },
  {
    "id": 45247465,
    "by": "4ad",
    "timeISO": "2025-09-15T08:40:13.000Z",
    "textPlain": "It would also be a useless article. It's fine to write for an audience, if you're not in the target audience, move on.",
    "parent": 45246855,
    "depth": 2
  },
  {
    "id": 45247768,
    "by": "Vosporos",
    "timeISO": "2025-09-15T09:29:11.000Z",
    "textPlain": "It's okay not to know things",
    "parent": 45246855,
    "depth": 2
  },
  {
    "id": 45247357,
    "by": "actionfromafar",
    "timeISO": "2025-09-15T08:22:24.000Z",
    "textPlain": "Yeah... meanwhile, in lesser languages, type classes is all we have.",
    "parent": 45246855,
    "depth": 2
  },
  {
    "id": 45248113,
    "by": "ioasuncvinvaer",
    "timeISO": "2025-09-15T10:28:02.000Z",
    "textPlain": "How does this compose iterators?",
    "parent": 45247714,
    "depth": 2
  },
  {
    "id": 45248173,
    "by": "steve_gh",
    "timeISO": "2025-09-15T10:38:15.000Z",
    "textPlain": "There is a really interesting interview with Simon Peyton-Jones referenced on HN yesterday.He talks a lot about why Haskell came about, and some of the thinking behind the design choices that were made.https://news.ycombinator.com/item?id=45242530",
    "parent": 45247653,
    "depth": 2
  },
  {
    "id": 45247891,
    "by": "skrebbel",
    "timeISO": "2025-09-15T09:47:32.000Z",
    "textPlain": "It's okay not to know things",
    "parent": 45247653,
    "depth": 2
  },
  {
    "id": 45248087,
    "by": "professor_v",
    "timeISO": "2025-09-15T10:22:35.000Z",
    "textPlain": "\"A monad is just a monoid in the category of endofunctors\"",
    "parent": 45247653,
    "depth": 2
  },
  {
    "id": 45248159,
    "by": "DaiPlusPlus",
    "timeISO": "2025-09-15T10:34:08.000Z",
    "textPlain": "\"Hello I would like x<-[1,2..] apples please\"",
    "parent": 45247653,
    "depth": 2
  }
]