[
  {
    "id": 45491211,
    "by": "netdur",
    "timeISO": "2025-10-06T13:28:48.000Z",
    "textPlain": "Any idea what kind of server we’d need to handle 40M users if it’s just text chat (no files or audio)?",
    "parent": 45490439,
    "depth": 1
  },
  {
    "id": 45491094,
    "by": "Semaphor",
    "timeISO": "2025-10-06T13:19:13.000Z",
    "textPlain": "I’ve been running Prosody [0] for many years now. Don’t ask me why I chose it over another server. I used to have a jabber.org account that I used before that, already back when I could use jabber to communicate with gchat and facebook messenger users. Alas, nowadays, it’s just my wife I use it to communicate with :([0]: https://prosody.im/",
    "parent": 45490439,
    "depth": 1
  },
  {
    "id": 45491022,
    "by": "sroerick",
    "timeISO": "2025-10-06T13:10:57.000Z",
    "textPlain": "I couldn't get iOS notifications to work properly when I tried to set up ejabberd.Ended up using Hey, and it works pretty well, I guess, but a rails PWA is a little heavy duty for my taste, I would prefer XMPP",
    "parent": 45490439,
    "depth": 1
  },
  {
    "id": 45490995,
    "by": "codedge",
    "timeISO": "2025-10-06T13:08:31.000Z",
    "textPlain": "Thanks! Same for me, it just works. Even regular updates run smoothly with ejabberd. I also do audio calls with it, and it is just a pleasant experience.",
    "parent": 45490439,
    "depth": 1
  },
  {
    "id": 45490564,
    "by": "mindcrime",
    "timeISO": "2025-10-06T12:21:44.000Z",
    "textPlain": "Good stuff. I run my own ejabberd server and it's been great. Installation is relatively straightforward, configuration isn't terribly convoluted, and it \"just works\" once up and running. Now my server doesn't have a ton of load on it, as it's used mainly for development / experimental purposes at the moment, so I can't say much about it's scalability or anything. But generally speaking, I installed it, did the initial setup, and other than adding/modifying users, I've rarely had to think about it since.",
    "parent": 45490439,
    "depth": 1
  },
  {
    "id": 45491001,
    "by": "endre",
    "timeISO": "2025-10-06T13:09:04.000Z",
    "textPlain": "the only problem, as usual, is the network effect",
    "parent": 45490439,
    "depth": 1
  },
  {
    "id": 45491126,
    "by": "codedge",
    "timeISO": "2025-10-06T13:21:39.000Z",
    "textPlain": "I cannot say, that I have problems with it. I use monal on iOS and whenever someone mentions me, I get a notification.",
    "parent": 45491022,
    "depth": 2
  },
  {
    "id": 45491212,
    "by": "netsharc",
    "timeISO": "2025-10-06T13:28:51.000Z",
    "textPlain": "Maybe for friends and family? But then, if their phone might be compromised by the state...And telling friends and family they need to setup a Jabber connection to talk you will make you \"That guy/girl who...\". And if the idea spreads, then talking to n people requires n accounts on n servers. At least Pidgin (last time I used it, which was last decade) supports such a configuration. I wonder if the mobile apps can do the same.",
    "parent": 45491001,
    "depth": 2
  },
  {
    "id": 45491150,
    "by": "tcfhgj",
    "timeISO": "2025-10-06T13:23:43.000Z",
    "textPlain": "what about- single point of failure of rooms (server creating the chat room)- media access via 3rd party servers- gossiping encrypted message access across multiple devices- encrypted audio-visual (group) communication- good clients for iOS- reliable server-side storage of messages (of all(!) chats)",
    "parent": 45491001,
    "depth": 2
  }
]