[
  {
    "id": 45926133,
    "by": "wongarsu",
    "timeISO": "2025-11-14T12:30:24.000Z",
    "textPlain": "I was mostly surprised by the \"Gnome 50\" part. Last I remembered Gnome was still version 3. Turns out they jumped from 3.38 to version 40",
    "parent": 45925950,
    "depth": 1
  },
  {
    "id": 45926186,
    "by": "mx7zysuj4xew",
    "timeISO": "2025-11-14T12:38:06.000Z",
    "textPlain": "X11 is not going anywhere. If anything it's Gnome adding another nail to its coffin",
    "parent": 45925950,
    "depth": 1
  },
  {
    "id": 45926220,
    "by": "gabrielgio",
    "timeISO": "2025-11-14T12:43:43.000Z",
    "textPlain": "x11 is in maintenance mode at this point and Gnome is not going anywhere. Gnome is used (and financed) by major distributions.Nothing new is being created with x11 and the people from freedesktop don't seen to be thrilled to maintain it. I don't think should change just for the sake of changing, but  I'd start looking to migrate whatever you use that depends on x11.",
    "parent": 45926186,
    "depth": 2
  }
]